odoo/addons/product_configurator_mrp/README.rst
odoo/addons/product_configurator_mrp/__init__.py
odoo/addons/product_configurator_mrp/__manifest__.py
odoo/addons/product_configurator_mrp/data/menu_product.xml
odoo/addons/product_configurator_mrp/demo/product_template.xml
odoo/addons/product_configurator_mrp/i18n/de.po
odoo/addons/product_configurator_mrp/i18n/it.po
odoo/addons/product_configurator_mrp/i18n/product_configurator_mrp.pot
odoo/addons/product_configurator_mrp/models/__init__.py
odoo/addons/product_configurator_mrp/models/mrp.py
odoo/addons/product_configurator_mrp/models/product_config.py
odoo/addons/product_configurator_mrp/readme/CONTRIBUTORS.md
odoo/addons/product_configurator_mrp/readme/DESCRIPTION.md
odoo/addons/product_configurator_mrp/security/configurator_security.xml
odoo/addons/product_configurator_mrp/security/ir.model.access.csv
odoo/addons/product_configurator_mrp/static/description/icon.png
odoo/addons/product_configurator_mrp/static/description/index.html
odoo/addons/product_configurator_mrp/static/src/js/config_button_mixin.esm.js
odoo/addons/product_configurator_mrp/static/src/js/form_controller.esm.js
odoo/addons/product_configurator_mrp/static/src/js/kanban_controller.esm.js
odoo/addons/product_configurator_mrp/static/src/js/list_controller.esm.js
odoo/addons/product_configurator_mrp/static/src/scss/mrp_config.scss
odoo/addons/product_configurator_mrp/static/src/xml/mrp_production_views.xml
odoo/addons/product_configurator_mrp/tests/__init__.py
odoo/addons/product_configurator_mrp/tests/test_mrp.py
odoo/addons/product_configurator_mrp/views/mrp_view.xml
odoo/addons/product_configurator_mrp/wizard/__init__.py
odoo/addons/product_configurator_mrp/wizard/product_configurator_mrp.py
odoo_addon_product_configurator_mrp-18.0.1.0.0.2.dist-info/METADATA
odoo_addon_product_configurator_mrp-18.0.1.0.0.2.dist-info/WHEEL
odoo_addon_product_configurator_mrp-18.0.1.0.0.2.dist-info/top_level.txt
odoo_addon_product_configurator_mrp-18.0.1.0.0.2.dist-info/RECORD
